llama_index/postprocessor/alibabacloud_aisearch_rerank/__init__.py
llama_index/postprocessor/alibabacloud_aisearch_rerank/base.py
llama_index_postprocessor_alibabacloud_aisearch_rerank-0.3.1.dist-info/METADATA
llama_index_postprocessor_alibabacloud_aisearch_rerank-0.3.1.dist-info/WHEEL
llama_index_postprocessor_alibabacloud_aisearch_rerank-0.3.1.dist-info/licenses/LICENSE
llama_index_postprocessor_alibabacloud_aisearch_rerank-0.3.1.dist-info/RECORD
