Metadata-Version: 2.4
Name: llama-index-postprocessor-alibabacloud-aisearch-rerank
Version: 0.3.1
Summary: llama-index postprocessor alibabacloud_aisearch_rerank integration
Author: llama-index
License-Expression: MIT
License-File: LICENSE
Requires-Python: <4.0,>=3.9
Requires-Dist: alibabacloud-searchplat20240529<2,>=1.1.0
Requires-Dist: llama-index-core<0.15,>=0.13.0
